quarto_tools/__init__.py
quarto_tools/bibtex.py
quarto_tools/cli.py
quarto_tools/toc.py
quarto_tools/utils.py
quarto_tools/xref.py
quarto_tools-1.0.0.dist-info/licenses/LICENSE
quarto_tools-1.0.0.dist-info/METADATA
quarto_tools-1.0.0.dist-info/WHEEL
quarto_tools-1.0.0.dist-info/entry_points.txt
quarto_tools-1.0.0.dist-info/top_level.txt
quarto_tools-1.0.0.dist-info/RECORD
