Metadata-Version: 2.4
Name: quarto-tools
Version: 1.0.0
Summary: Utilities for working with Quarto projects (PDF TOC, trimmed BibTeX file, cross-reference audit.)
Author-email: Stephen J Mildehall <mynl@me.com>
License-Expression: MIT
Project-URL: Homepage, https://github.com/mynl/quarto_tools_project
Classifier: Development Status :: 4 - Beta
Classifier: Programming Language :: Python :: 3
Classifier: Programming Language :: Python :: 3.13
Requires-Python: >=3.13
License-File: LICENSE
Requires-Dist: pandas>=2.2
Requires-Dist: greater-tables
Provides-Extra: dev
Requires-Dist: pytest>=8; extra == "dev"
Requires-Dist: ruff>=0.5; extra == "dev"
Dynamic: license-file
